{
    "donut": {
        "series": [],
        "chart": {
        "type": "donut"
        }   
    },
    
    "group_column": {
      "series": [],
      "chart": {
      "type": "bar",
      "height": 430
    },
    "plotOptions": {
      "bar": {
        "horizontal": true,
        "dataLabels": {
          "position": "top"
        }
      }
    },
    "dataLabels": {
      "enabled": true,

      "offsetX": -6,
      "style": {
        "fontSize": "10px",
        "colors": ["#000"]
      }
    },
    "tooltip": {
      "enabled": true,
      "y": {
        "formatter": null
      }
    },
    "stroke": {
      "show": true,
      "width": 1,
      "colors": ["#fff"]
    },
    "xaxis": {
      "categories": []
    },
    "legend": {
      "onItemHover": {
        "highlightDataSeries": true
      },
      "position": "bottom"
    },
    "title": {
      "text": "Top and Least Device",
      "align": "left",
      "floating": true
    }
    },

    "dynamic_column":{
      "theme": {
       
      },
      "title":{
        "text": "",
        "align": "center"
      },
      "series": [],
      "chart": {
        "type": "bar",
        "height": 400,
        "stacked": true,
        "stackType": "100%",
        "toolbar": {
          "show": true
        },
        "zoom": {
          "enabled": true
        }
      },
      "plotOptions": {
        "bar": {
          "horizontal": false
        }
      },
      "dataLabels": {
        "enabled": true,
        "textAnchor": "middle"
      },
      "xaxis": {
        "categories": []
      },
      "legend": {
        "position": "right",
        "offsetX": 0,
        "offsetY": 150,
        "markers":{
          "fillColors": ["#ffc4a3","#ff9a76","#f96d80","#bb596b","#e7305b"]
        }
      },
      "fill": {
        "opacity": 1,
        "colors": ["#ffc4a3","#ff9a76","#f96d80","#bb596b","#e7305b"]
      },
      "tooltip":{
        "marker":{
          "fillColors": ["#ffc4a3","#ff9a76","#f96d80","#bb596b","#e7305b"]
        }
      }
  }
}