{
    "theme": {
     
    },
    "title":{
      "text": "",
      "align": "center"
    },
    "series": [],
    "chart": {
      "type": "bar",
      "height": 400,
      "stacked": true,
      "stackType": "100%",
      "toolbar": {
        "show": true
      },
      "zoom": {
        "enabled": true
      }
    },
    "plotOptions": {
      "bar": {
        "horizontal": false
      }
    },
    "dataLabels": {
      "enabled": true,      
      "position":"top",
      "horizontalAlign": "center"
    },
    "xaxis": {
      "categories": []
    },
    "legend": {
      "position": "top",
      "horizontalAlign": "center",
      "offsetX": 0,
      "offsetY": 150,
      "markers":{
        "fillColors":["#3498DB", "#2ECC71", "#F1C40F", "#E67E22", "#E74C3C"]
      }
    },
    "fill": {
      "opacity": 1,
      "colors":["#3498DB", "#2ECC71", "#F1C40F", "#E67E22", "#E74C3C"]
    },
    "tooltip":{
      "marker":{
        "fillColors":["#3498DB", "#2ECC71", "#F1C40F", "#E67E22", "#E74C3C"]
      }
    }
}